.clang-format
.flake8
.gitignore
.gitmodules
CHANGELOG.md
CODEOWNERS
CODE_OF_CONDUCT
Dockerfile
Dockerfile-cuda
Dockerfile-embedded
LICENSE
MANIFEST.in
Makefile
README.md
__init__.py
description.txt
packages.txt
setup.py
./src/opendr/__init__.py
./src/opendr/_setup.py
./src/opendr/_version.py
./src/opendr/control/__init__.py
./src/opendr/engine/__init__.py
./src/opendr/engine/constants.py
./src/opendr/engine/data.py
./src/opendr/engine/datasets.py
./src/opendr/engine/example_learner.py
./src/opendr/engine/learners.py
./src/opendr/engine/target.py
./src/opendr/perception/__init__.py
./src/opendr/planning/__init__.py
./src/opendr/simulation/__init__.py
./src/opendr/simulation/human_model_generation/README.md
./src/opendr/simulation/human_model_generation/__init__.py
./src/opendr/simulation/human_model_generation/dependencies.ini
./src/opendr/simulation/human_model_generation/pifu_generator_learner.py
./src/opendr/simulation/human_model_generation/utilities/__init__.py
./src/opendr/simulation/human_model_generation/utilities/config_utils.py
./src/opendr/simulation/human_model_generation/utilities/joint_extractor.py
./src/opendr/simulation/human_model_generation/utilities/model_3D.py
./src/opendr/simulation/human_model_generation/utilities/studio.py
./src/opendr/simulation/human_model_generation/utilities/visualizer.py
./src/opendr/simulation/human_model_generation/utilities/PIFu/LICENSE.txt
./src/opendr/simulation/human_model_generation/utilities/PIFu/__init__.py
./src/opendr/simulation/human_model_generation/utilities/PIFu/pifu_funcs.py
./src/opendr/simulation/human_model_generation/utilities/PIFu/pifu_inference.py
./src/opendr/simulation/human_model_generation/utilities/PIFu/apps/__init__.py
./src/opendr/simulation/human_model_generation/utilities/PIFu/apps/crop_img.py
./src/opendr/simulation/human_model_generation/utilities/PIFu/apps/eval.py
./src/opendr/simulation/human_model_generation/utilities/PIFu/apps/prt_util.py
./src/opendr_toolkit_human_model_generation.egg-info/PKG-INFO
./src/opendr_toolkit_human_model_generation.egg-info/SOURCES.txt
./src/opendr_toolkit_human_model_generation.egg-info/dependency_links.txt
./src/opendr_toolkit_human_model_generation.egg-info/requires.txt
./src/opendr_toolkit_human_model_generation.egg-info/top_level.txt
